geezify-python-main/LICENSE
geezify-python-main/README.md
geezify-python-main/arabify.py
geezify-python-main/arabify_test.py
geezify-python-main/geezify.py
geezify-python-main/geezify_test.py
geezify-python-main/test_data.py
scripturelookup/__init__.py
scripturelookup/command_line.py
scripturelookup/data.py
scripturelookup/lookup.py
scripturelookup/numbers.py
scripturelookup/data/metadata-languages.min.json
scripturelookup/data/metadata-scriptures.min.json
scripturelookup-0.0.5.dist-info/licenses/LICENSE
scripturelookup-0.0.5.dist-info/METADATA
scripturelookup-0.0.5.dist-info/WHEEL
scripturelookup-0.0.5.dist-info/entry_points.txt
scripturelookup-0.0.5.dist-info/top_level.txt
scripturelookup-0.0.5.dist-info/RECORD
