Metadata-Version: 2.4
Name: scripturelookup
Version: 0.0.5
Summary: Python and command-line utility for converting scripture references between formats.
Author-email: Samuel Bradshaw <samuel.h.bradshaw@gmail.com>
License: MIT License
Project-URL: Repository, https://github.com/samuelbradshaw/python-scripture-lookup
Project-URL: Issues, https://github.com/samuelbradshaw/python-scripture-lookup/issues
Project-URL: Changelog, https://github.com/samuelbradshaw/python-scripture-lookup/releases
Keywords: python,command,scripture,bible,book of mormon,reference
Classifier: License :: OSI Approved :: MIT License
Classifier: Programming Language :: Python :: 3
Requires-Python: >=3.8
License-File: LICENSE
Requires-Dist: requests
Dynamic: license-file
